Metadata-Version: 2.1
Name: free-pygpt
Version: 1.3.2
Summary: Library for use free gpt 3.5 in python
Home-page: https://github.com/nxSlayer/free_gpt
Author: nxSlayer
Author-email: princediscordslay@gmail.com
License: MIT
Keywords: free_pygpt,free-gpt,freegpt,free_gpt.py,free_gpt
Requires-Python: >=3.6
